toolkit/__init__.py
toolkit/main.py
toolkit/shodan/__init__.py
toolkit/shodan/__main__.py
toolkit/shodan/client.py
toolkit/shodan/helpers.py
toolkit/shodan/stream.py
toolkit/shodan/threatnet.py
toolkit/shodan/cli/__init__.py
toolkit/shodan/cli/alert.py
toolkit/shodan/cli/data.py
toolkit/shodan/cli/helpers.py
toolkit/shodan/cli/host.py
toolkit/shodan/cli/organization.py
toolkit/shodan/cli/scan.py
toolkit/shodan/cli/settings.py
toolkit/shodan/cli/worldmap.py
toolkit/shodan/cli/converter/__init__.py
toolkit/shodan/cli/converter/base.py
toolkit/shodan/cli/converter/csvc.py
toolkit/shodan/cli/converter/excel.py
toolkit/shodan/cli/converter/geojson.py
toolkit/shodan/cli/converter/images.py
toolkit/shodan/cli/converter/kml.py
toolkit/urlscan/__init__.py
toolkit/urlscan/__main__.py
toolkit/urlscan/urlscan.py
toolkit/urlscan/utils.py
toolkit/virustotal/__init__.py
toolkit/virustotal/client.py
toolkit/virustotal/error.py
toolkit/virustotal/feed.py
toolkit/virustotal/iterator.py
toolkit/virustotal/object.py
toolkit/virustotal/utils.py
toolkit/virustotal/version.py
security_toolkit-0.4.dist-info/LICENSE
security_toolkit-0.4.dist-info/METADATA
security_toolkit-0.4.dist-info/WHEEL
security_toolkit-0.4.dist-info/entry_points.txt
security_toolkit-0.4.dist-info/top_level.txt
security_toolkit-0.4.dist-info/RECORD
